ffmpeg_progress_yield/__init__.py
ffmpeg_progress_yield/__main__.py
ffmpeg_progress_yield/ffmpeg_progress_yield.py
ffmpeg_progress_yield/py.typed
ffmpeg_progress_yield-1.1.0.dist-info/licenses/LICENSE.md
ffmpeg_progress_yield-1.1.0.dist-info/WHEEL
ffmpeg_progress_yield-1.1.0.dist-info/entry_points.txt
ffmpeg_progress_yield-1.1.0.dist-info/METADATA
ffmpeg_progress_yield-1.1.0.dist-info/RECORD
